plotdigitizer/__init__.py
plotdigitizer/geometry.py
plotdigitizer/grid.py
plotdigitizer/locate.py
plotdigitizer/plotdigitizer.py
plotdigitizer/trajectory.py
plotdigitizer-0.3.0.dist-info/entry_points.txt
plotdigitizer-0.3.0.dist-info/LICENSE
plotdigitizer-0.3.0.dist-info/METADATA
plotdigitizer-0.3.0.dist-info/WHEEL
plotdigitizer-0.3.0.dist-info/RECORD
