Metadata-Version: 2.1
Name: plotdigitizer
Version: 0.3.0
Summary: Extract raw data from plots images
Home-page: https://github.com/dilawar/PlotDigitizer
License: LGPL-3.0-or-later
Author: Dilawar Singh
Author-email: dilawar.s.rajput@gmail.com
Maintainer: Dilawar Singh
Maintainer-email: dilawar.s.rajput@gmail.com
Requires-Python: >=3.9,<=4
Classifier: License :: OSI Approved :: GNU Lesser General Public License v3 or later (LGPLv3+)
Classifier: Programming Language :: Python :: 3
Classifier: Programming Language :: Python :: 3.9
Classifier: Programming Language :: Python :: 3.10
Classifier: Programming Language :: Python :: 3.11
Requires-Dist: matplotlib (>=3.9.1,<4.0.0)
Requires-Dist: numpy (>=2.0.0,<3.0.0)
Requires-Dist: opencv-python (>=4.10,<5.0)
Project-URL: Repository, https://github.com/dilawar/PlotDigitizer
